stringsifter/flarestrings.py
stringsifter/lib/__init__.py
stringsifter/lib/constants.json
stringsifter/lib/lid.176.ftz
stringsifter/lib/markov.pkl
stringsifter/lib/stats.py
stringsifter/lib/util.py
stringsifter/model/featurizer.pkl
stringsifter/model/ranker.pkl
stringsifter/preprocess.py
stringsifter/rank_strings.py
stringsifter/version.py
stringsifter-3.20230711.dist-info/LICENSE
stringsifter-3.20230711.dist-info/METADATA
stringsifter-3.20230711.dist-info/WHEEL
stringsifter-3.20230711.dist-info/entry_points.txt
stringsifter-3.20230711.dist-info/RECORD
