Metadata-Version: 2.1
Name: stringsifter
Version: 3.20230711
Summary: StringSifter is a machine learning tool that automatically ranks strings based on their relevance for malware analysis.
Home-page: https://github.com/mandiant/stringsifter
License: Apache-2.0
Author: Mandiant Data Science Research
Requires-Python: >=3.9,<4.0
Classifier: License :: OSI Approved :: Apache Software License
Classifier: Programming Language :: Python :: 3
Classifier: Programming Language :: Python :: 3.9
Classifier: Programming Language :: Python :: 3.10
Classifier: Programming Language :: Python :: 3.11
Requires-Dist: fasttext-wheel (>=0.9.2,<0.10.0)
Requires-Dist: joblib (>=1.3.1,<1.4.0)
Requires-Dist: lightgbm (>=3.1,<4.0)
Requires-Dist: numpy (==1.24.4)
Requires-Dist: scikit-learn (>=1.3.0,<1.4.0)
Project-URL: Repository, https://github.com/mandiant/stringsifter
